bhsenti/__init__.py
bhsenti/onnx/vocab.txt
bhsenti-0.0.3.dist-info/LICENSE
bhsenti-0.0.3.dist-info/METADATA
bhsenti-0.0.3.dist-info/WHEEL
bhsenti-0.0.3.dist-info/top_level.txt
bhsenti-0.0.3.dist-info/RECORD
