Metadata-Version: 2.1
Name: bhsenti
Version: 0.0.3
Summary: 基于三分类的中文情感分析
Author-email: bhnw <bhshare.cn@gmail.com>
Project-URL: Homepage, https://github.com/yaokui2018
Project-URL: Bug Tracker, https://github.com/yaokui2018/bhsenti/issues
Classifier: Programming Language :: Python :: 3
Classifier: License :: OSI Approved :: GNU General Public License v3 (GPLv3)
Classifier: Operating System :: OS Independent
Requires-Python: >=3
License-File: LICENSE
Requires-Dist: transformers
Requires-Dist: onnxruntime
Requires-Dist: requests
Requires-Dist: tqdm
